COPYING
MANIFEST.in
README.rst
setup.py
chainable_validators.egg-info/PKG-INFO
chainable_validators.egg-info/SOURCES.txt
chainable_validators.egg-info/dependency_links.txt
chainable_validators.egg-info/pbr.json
chainable_validators.egg-info/top_level.txt
validators/__init__.py
validators/chain.py
validators/helpers.py
validators/re_patterns.py
validators/validators.py