Metadata-Version: 1.1
Name: chainable-validators
Version: 0.6
Summary: Python data validation framework that uses chainable validator
Home-page: https://github.com/Outernet-Project/chainable-validators
Author: Outernet Inc
Author-email: apps@outernet.is
License: GPLv3
Keywords: validation,framework,method chaining
Platform: UNKNOWN
Classifier: Development Status :: 3 - Alpha
Classifier: License :: OSI Approved :: GNU Lesser General Public License v3 or later (LGPLv3+)
Classifier: Programming Language :: Python :: 2.7
Classifier: Programming Language :: Python :: 3.4
Classifier: Topic :: Utilities
